{"blocks":{"languageVersion":0,"blocks":[{"type":"start","id":"AP#6~HVih?O0{fgzc{Cv","x":345,"y":345,"fields":{"BUTTON":"СТАРТ"},"next":{"block":{"type":"variables_set","id":"U+B/x++JK{;qlBq_KMy]","fields":{"VAR":{"id":";gfWa:Tt6[Ysgv_ctQBW"}},"inputs":{"VALUE":{"block":{"type":"math_number","id":"ZM;dV0G8`LhpT``7{2}`","fields":{"NUM":2}}}},"next":{"block":{"type":"variables_set","id":"ij59%M%*bT66_Ppl|puy","fields":{"VAR":{"id":"*5Uu%j-I#v^W-FBLLtFA"}},"inputs":{"VALUE":{"block":{"type":"math_number","id":"$~~f^!7vpN`-bt)qQ`ZU","fields":{"NUM":13}}}},"next":{"block":{"type":"pinmode","id":"Fb(}HzwaW!BkQYwl_Yp_","fields":{"MODE":"0"},"inputs":{"PIN":{"block":{"type":"variables_get","id":"{vDuq5J#?odxNPuZNLNm","fields":{"VAR":{"id":";gfWa:Tt6[Ysgv_ctQBW"}}}}},"next":{"block":{"type":"pinmode","id":".E:?p}NLGb1@q*%|xL+t","fields":{"MODE":"1"},"inputs":{"PIN":{"block":{"type":"variables_get","id":"64-)({KchpmHHFV363;u","fields":{"VAR":{"id":"*5Uu%j-I#v^W-FBLLtFA"}}}}},"next":{"block":{"type":"controls_whileUntil","id":"Bs!MWQ4PXtXWl5:{8g;u","fields":{"MODE":"WHILE"},"inputs":{"BOOL":{"block":{"type":"logic_boolean","id":"tL_#d(5HtR)Ej|7{luBj","fields":{"BOOL":"TRUE"}}},"DO":{"block":{"type":"controls_ifelse","id":".Vu`:n=]@,D%^0J,PtKh","inputs":{"IF0":{"block":{"type":"logic_compare","id":"{X}4FUG{h:m[C^t[}KlN","fields":{"OP":"EQ"},"inputs":{"A":{"block":{"type":"math_number","id":"HhdS-8yB1F_ngjFw%J::","fields":{"NUM":1}}},"B":{"block":{"type":"digital_read","id":"Y8Zmd31=I8!]R!rz}~Up","inputs":{"NUM":{"block":{"type":"variables_get","id":"R90_[~+mbZGaLeftO%;d","fields":{"VAR":{"id":";gfWa:Tt6[Ysgv_ctQBW"}}}}}}}}}},"DO0":{"block":{"type":"digital_write","id":"xPa)Tu4uB#!!}Ecdwxc;","fields":{"MODE":"1"},"inputs":{"PIN":{"block":{"type":"variables_get","id":"RG%iA~)`pWwaXa|*C5^u","fields":{"VAR":{"id":"*5Uu%j-I#v^W-FBLLtFA"}}}}}}},"ELSE":{"block":{"type":"digital_write","id":"Uo#=AN(D,]USrxQ+c1!%","fields":{"MODE":"0"},"inputs":{"PIN":{"block":{"type":"variables_get","id":"fsz,5Io{t{ymG{WI];EO","fields":{"VAR":{"id":"*5Uu%j-I#v^W-FBLLtFA"}}}}}}}}}}}}}}}}}}}}}}]},"variables":[{"name":"button_pin","id":";gfWa:Tt6[Ysgv_ctQBW"},{"name":"pin","id":"*5Uu%j-I#v^W-FBLLtFA"},{"name":"элемент","id":"d2,Vv6{L?6*;fdBW^5KL"}]}